transaction_analysis_module.py
transaction_analysis_test_upload-0.1.0.dist-info/METADATA
transaction_analysis_test_upload-0.1.0.dist-info/WHEEL
transaction_analysis_test_upload-0.1.0.dist-info/entry_points.txt
transaction_analysis_test_upload-0.1.0.dist-info/top_level.txt
transaction_analysis_test_upload-0.1.0.dist-info/RECORD
